karrio/mappers/amazon_shipping/__init__.py
karrio/mappers/amazon_shipping/mapper.py
karrio/mappers/amazon_shipping/proxy.py
karrio/mappers/amazon_shipping/settings.py
karrio/plugins/amazon_shipping/__init__.py
karrio/providers/amazon_shipping/__init__.py
karrio/providers/amazon_shipping/error.py
karrio/providers/amazon_shipping/rate.py
karrio/providers/amazon_shipping/tracking.py
karrio/providers/amazon_shipping/units.py
karrio/providers/amazon_shipping/utils.py
karrio/providers/amazon_shipping/shipment/__init__.py
karrio/providers/amazon_shipping/shipment/cancel.py
karrio/providers/amazon_shipping/shipment/create.py
karrio/schemas/amazon_shipping/__init__.py
karrio/schemas/amazon_shipping/cancel_shipment_response.py
karrio/schemas/amazon_shipping/error_response.py
karrio/schemas/amazon_shipping/one_click_shipment_request.py
karrio/schemas/amazon_shipping/one_click_shipment_response.py
karrio/schemas/amazon_shipping/purchase_shipment_request.py
karrio/schemas/amazon_shipping/purchase_shipment_response.py
karrio/schemas/amazon_shipping/rate_request.py
karrio/schemas/amazon_shipping/rate_response.py
karrio/schemas/amazon_shipping/tracking_response.py
karrio_amazon_shipping-2026.1.4.dist-info/METADATA
karrio_amazon_shipping-2026.1.4.dist-info/WHEEL
karrio_amazon_shipping-2026.1.4.dist-info/entry_points.txt
karrio_amazon_shipping-2026.1.4.dist-info/top_level.txt
karrio_amazon_shipping-2026.1.4.dist-info/RECORD
